[
  {
    "match": "Crystal Palace FC vs Chelsea FC",
    "date": "2026-01-25",
    "tip": "No Clear Favorite",
    "confidence": "47.2%"
  },
  {
    "match": "Brentford FC vs Nottingham Forest FC",
    "date": "2026-01-25",
    "tip": "Home Win",
    "confidence": "63.8%"
  },
  {
    "match": "Newcastle United FC vs Aston Villa FC",
    "date": "2026-01-25",
    "tip": "No Clear Favorite",
    "confidence": "53.7%"
  },
  {
    "match": "Arsenal FC vs Manchester United FC",
    "date": "2026-01-25",
    "tip": "No Clear Favorite",
    "confidence": "50.2%"
  },
  {
    "match": "Everton FC vs Leeds United FC",
    "date": "2026-01-26",
    "tip": "No Clear Favorite",
    "confidence": "53.1%"
  },
  {
    "match": "Brighton & Hove Albion FC vs Everton FC",
    "date": "2026-01-31",
    "tip": "No Clear Favorite",
    "confidence": "42.5%"
  },
  {
    "match": "Leeds United FC vs Arsenal FC",
    "date": "2026-01-31",
    "tip": "No Clear Favorite",
    "confidence": "49.2%"
  },
  {
    "match": "Wolverhampton Wanderers FC vs AFC Bournemouth",
    "date": "2026-01-31",
    "tip": "No Clear Favorite",
    "confidence": "42.5%"
  },
  {
    "match": "Chelsea FC vs West Ham United FC",
    "date": "2026-01-31",
    "tip": "No Clear Favorite",
    "confidence": "42.5%"
  },
  {
    "match": "Liverpool FC vs Newcastle United FC",
    "date": "2026-01-31",
    "tip": "No Clear Favorite",
    "confidence": "53.1%"
  }
]